shiftregister.v
module shiftreg(a,lin,rin,clk,clr,i,select);
  output[3:0]a;
  input lin,rin,clk,clr;
  input[3:0]i;
  input[1:0]select;
  reg[3:0]a;
  
  always@(posedge clk or negedge clk)
  if(~clr)
    a=4'b0000;
  else
    case(select)
      2'b00:a=a;
      2'b01:a={rin,a[3:1]};
      2'b10:a={a[2:0],lin};
      2'b11:a=i;
    endcase
endmodule

module t_shift;
  reg lin,rin,clk,clr;
  reg[3:0]i;
  reg[1:0]select;
  wire[3:0]a;
  
  shiftreg f1(a,lin,rin,clk,clr,i,select);
  always #5 clk=~clk;
  
  initial 
    begin 
      $dumpfile("shift.vcd");
      $dumpvars(1,f1.shiftreg);
      $monitor("%b%b%b%b",a[3],a[2],a[1],a[0]);
      clk=1'b1;
      clr=1'b0;#10
      clr=1'b1;
      
      i=4'b0000;lin=0;rin=1;
      select=2'b00;#30
      repeat(4)#30 select=2'b01;
      repeat(2)#30 select =2'b10;
      select=2'b11;#30
      
      $finish;
    end
/*initial begin
	$dumpfile("out1.vcd");
	$dumpvars(1,uut.code);
end*/
endmodule

shift.vcd
$date
	Mon Oct 21 11:07:37 2019
$end
$version
	Icarus Verilog
$end
$timescale
	1s
$end
$scope module t_shift $end
$scope module f1 $end
$var wire 1 ! clk $end
$var wire 1 " clr $end
$var wire 4 # i [3:0] $end
$var wire 1 $ lin $end
$var wire 1 % rin $end
$var wire 2 & select [1:0] $end
$var reg 4 ' a [3:0] $end
$upscope $end
$upscope $end
$enddefinitions $end
#0
$dumpvars
b0 '
bx &
x%
x$
bx #
0"
1!
$end
#5
0!
#10
1!
b0 &
1%
0$
b0 #
1"
#15
0!
#20
1!
#25
0!
#30
1!
#35
0!
#40
1!
#45
0!
#50
1!
#55
0!
#60
1!
#65
0!
#70
b1000 '
1!
b1 &
#75
b1100 '
0!
#80
b1110 '
1!
#85
b1111 '
0!
#90
1!
#95
0!
#100
1!
#105
0!
#110
1!
#115
0!
#120
1!
#125
0!
#130
1!
#135
0!
#140
1!
#145
0!
#150
1!
#155
0!
#160
1!
#165
0!
#170
1!
#175
0!
#180
1!
#185
0!
#190
b1110 '
1!
b10 &
#195
b1100 '
0!
#200
b1000 '
1!
#205
b0 '
0!
#210
1!
#215
0!
#220
1!
b11 &
