counter.v
module binrip(q,clk,reset);
  output q;
  input clk,reset;
  reg q;
  
  always@(negedge clk or posedge reset )
  
  if(reset)
    q=1'b0;
  else
    q=~q;
    
endmodule

module bin(a0,a1,a2,clk,reset);
  output a0,a1,a2;
  input clk,reset;
  
  binrip f0(a0,clk,reset);
  binrip f1(a1,a0,reset);
  binrip f2(a2,a1,reset);
endmodule
module t_binrip;
  reg clk,reset;
  wire a0,a1,a2;
  
  bin b0(a0,a1,a2,clk,reset);
  always #5 clk=~clk;
  initial
    begin 
      $dumpfile("test3.vcd");
      $dumpvars(1,b0.bin);
      $monitor("%b %b %b",a2,a1,a0);
      clk=1'b0;
      reset=1'b1;
      
      #4
      reset =1'b0;
      #75
     
    $finish;
  end 
endmodule

test3.vcd
$date
	Mon Oct 21 11:08:28 2019
$end
$version
	Icarus Verilog
$end
$timescale
	1s
$end
$scope module t_binrip $end
$scope module b0 $end
$var wire 1 ! clk $end
$var wire 1 " reset $end
$var wire 1 # a2 $end
$var wire 1 $ a1 $end
$var wire 1 % a0 $end
$upscope $end
$upscope $end
$enddefinitions $end
#0
$dumpvars
0%
0$
0#
1"
0!
$end
#4
0"
#5
1!
#10
1%
0!
#15
1!
#20
1$
0%
0!
#25
1!
#30
1%
0!
#35
1!
#40
1#
0$
0%
0!
#45
1!
#50
1%
0!
#55
1!
#60
1$
0%
0!
#65
1!
#70
1%
0!
